simple_fernet/SimpleFernet.py
simple_fernet/__init__.py
simple_fernet-1.0.0.dist-info/METADATA
simple_fernet-1.0.0.dist-info/WHEEL
simple_fernet-1.0.0.dist-info/licenses/LICENSE
simple_fernet-1.0.0.dist-info/RECORD
