Metadata-Version: 2.4
Name: simple_fernet
Version: 1.0.0
Summary: A Python package that streamlines the process of encrypting and decrypting data with Fernet.
Project-URL: Homepage, https://github.com/darkroastcreative/simple-fernet
Project-URL: Repository, https://github.com/darkroastcreative/simple-fernet
Project-URL: Issues, https://github.com/darkroastcreative/simple-fernet/issues
Author-email: David Urso <david@darkroastcreative.co>
Maintainer-email: David Urso <david@darkroastcreative.co>
License-Expression: AGPL-3.0-only
License-File: LICENSE
Keywords: encryption,fernet,symmetric encryption
Classifier: Development Status :: 5 - Production/Stable
Classifier: License :: OSI Approved :: GNU Affero General Public License v3
Classifier: Operating System :: OS Independent
Classifier: Programming Language :: Python :: 3
Requires-Python: >=3.12
Requires-Dist: cryptography
